rl_labs/__init__.py
rl_labs/lab1_agent_environment.py
rl_labs/lab2_gridworld.py
rl_labs/lab3_mrp_monte_carlo.py
rl_labs/lab4_policy_evaluation.py
rl_labs/lab5_policy_improvement.py
rl_labs/lab6_value_iteration.py
rl_labs/lab7_td_learning.py
rl_labs/utils.py
rl_labs-1.0.0.dist-info/licenses/LICENSE
rl_labs-1.0.0.dist-info/METADATA
rl_labs-1.0.0.dist-info/WHEEL
rl_labs-1.0.0.dist-info/top_level.txt
rl_labs-1.0.0.dist-info/RECORD
